konso_dice_roller/__init__.py
konso_dice_roller/format.py
konso_dice_roller/interface.py
konso_dice_roller/math.py
konso_dice_roller/parse.py
konso_dice_roller/roll.py
konso_dice_roller-0.0.6.dist-info/LICENSE
konso_dice_roller-0.0.6.dist-info/METADATA
konso_dice_roller-0.0.6.dist-info/WHEEL
konso_dice_roller-0.0.6.dist-info/top_level.txt
konso_dice_roller-0.0.6.dist-info/RECORD
