Metadata-Version: 2.1
Name: konso-dice-roller
Version: 0.0.6
Summary: A simple dice roller library
Home-page: https://github.com/konsou/konso_dice_roller
Author: Tomi Javanainen
Author-email: tomi.javanainen@gmail.com
License: MIT
Project-URL: Source, https://github.com/konsou/konso_dice_roller
Platform: UNKNOWN
Classifier: Intended Audience :: Developers
Classifier: License :: OSI Approved :: MIT License
Classifier: Natural Language :: Finnish
Classifier: Operating System :: OS Independent
Classifier: Programming Language :: Python
Classifier: Programming Language :: Python :: 3
Classifier: Programming Language :: Python :: 3.8
Classifier: Programming Language :: Python :: 3.9
Classifier: Programming Language :: Python :: 3.10
Classifier: Programming Language :: Python :: 3.11
Classifier: Programming Language :: Python :: 3 :: Only
Classifier: Programming Language :: Python :: Implementation :: CPython
Classifier: Topic :: Software Development :: Libraries
Requires-Python: >=3.8, <4
License-File: LICENSE
